pywebcrawler/__init__.py
pywebcrawler/__main__.py
pywebcrawler/colorify.py
pywebcrawler/link_finder.py
pywebcrawler/requester.py
pywebcrawler/spider.py
pywebcrawler/utilities.py
pywebcrawler/data/mimetypes.txt
pywebcrawler/data/useragents.txt
pywebcrawler-0.0.1.dist-info/LICENSE
pywebcrawler-0.0.1.dist-info/METADATA
pywebcrawler-0.0.1.dist-info/WHEEL
pywebcrawler-0.0.1.dist-info/top_level.txt
pywebcrawler-0.0.1.dist-info/RECORD
