Metadata-Version: 2.1
Name: pywebcrawler
Version: 0.0.1
Summary: A fast web crawler to satisfy all your needs
Home-page: https://github.com/eckarthik/PyWebCrawler
Author: Karthik E C
Author-email: eckarthik39@gmail.com
License: UNKNOWN
Platform: UNKNOWN
Classifier: Programming Language :: Python :: 3
Classifier: License :: OSI Approved :: MIT License
Classifier: Operating System :: OS Independent
Requires-Python: >=3.6
Requires-Dist: requests
Requires-Dist: bs4
